sqlaurum/__init__.py
sqlaurum/_version.py
sqlaurum/dialects/__init__.py
sqlaurum/dialects/postgres.py
sqlaurum/dialects/sqlite.py
sqlaurum/function_elements.py
sqlaurum/py.typed
sqlaurum/repository.py
sqlaurum/sql_types.py
sqlaurum/types.py
sqlaurum/utils.py
sqlaurum-0.1.0.dist-info/LICENSE
sqlaurum-0.1.0.dist-info/METADATA
sqlaurum-0.1.0.dist-info/WHEEL
sqlaurum-0.1.0.dist-info/RECORD
