Metadata-Version: 2.1
Name: sqlaurum
Version: 0.1.0
Summary: SQLAlchemy session and query wrapper.
Author: Radzim Kowalow
Author-email: radzim.kowalow@performance-media.pl
Requires-Python: >=3.8.1,<4.0
Classifier: Programming Language :: Python :: 3
Classifier: Programming Language :: Python :: 3.9
Classifier: Programming Language :: Python :: 3.10
Classifier: Programming Language :: Python :: 3.11
Provides-Extra: aiosqlite
Provides-Extra: alembic
Provides-Extra: all
Provides-Extra: asyncpg
Requires-Dist: SQLAlchemy (>=2.0.2,<3.0.0)
Requires-Dist: aiosqlite (>=0.18.0,<0.19.0) ; extra == "all" or extra == "aiosqlite"
Requires-Dist: alembic (>=1.10.1,<2.0.0) ; extra == "all" or extra == "alembic"
Requires-Dist: asyncpg (>=0.27.0,<0.28.0) ; extra == "all" or extra == "asyncpg"
